AUTHORS
MANIFEST.in
README.md
setup.py
isittor/__init__.py
isittor/__main__.py
isittor/isittor.py
isittor.egg-info/PKG-INFO
isittor.egg-info/SOURCES.txt
isittor.egg-info/dependency_links.txt
isittor.egg-info/entry_points.txt
isittor.egg-info/requires.txt
isittor.egg-info/top_level.txt