Metadata-Version: 1.1
Name: isittor
Version: 1.2
Summary: Check if the given <IPaddress> is a Tor exit node.
Home-page: https://github.com/nicolargo/isittor
Author: Nicolas Hennion
Author-email: nicolas@nicolargo.com
License: MIT
Keywords: cli tor
Platform: UNKNOWN
Classifier: Development Status :: 4 - Beta
Classifier: Environment :: Console
Classifier: Intended Audience :: End Users/Desktop
Classifier: License :: OSI Approved :: MIT License
Classifier: Operating System :: OS Independent
Classifier: Natural Language :: English
Classifier: Operating System :: OS Independent
Classifier: Programming Language :: Python :: 2
Classifier: Topic :: Utilities
